mwdb/__init__.py
mwdb/app.py
mwdb/paths.py
mwdb/version.py
mwdb/cli/__init__.py
mwdb/cli/base.py
mwdb/cli/cli.py
mwdb/cli/configuration.py
mwdb/cli/database.py
mwdb/cli/web.py
mwdb/core/__init__.py
mwdb/core/app.py
mwdb/core/auth.py
mwdb/core/capabilities.py
mwdb/core/config.py
mwdb/core/deprecated.py
mwdb/core/hooks.py
mwdb/core/karton.py
mwdb/core/log.py
mwdb/core/mail.py
mwdb/core/plugins.py
mwdb/core/rate_limit.py
mwdb/core/service.py
mwdb/core/static.py
mwdb/core/util.py
mwdb/core/metrics/__init__.py
mwdb/core/metrics/redis_counter.py
mwdb/core/oauth/__init__.py
mwdb/core/oauth/client.py
mwdb/core/oauth/provider.py
mwdb/core/search/__init__.py
mwdb/core/search/exceptions.py
mwdb/core/search/fields.py
mwdb/core/search/mappings.py
mwdb/core/search/node_to_value.py
mwdb/core/search/parse_helpers.py
mwdb/core/search/search.py
mwdb/model/__init__.py
mwdb/model/api_key.py
mwdb/model/attribute.py
mwdb/model/blob.py
mwdb/model/comment.py
mwdb/model/config.py
mwdb/model/file.py
mwdb/model/group.py
mwdb/model/karton.py
mwdb/model/oauth.py
mwdb/model/object.py
mwdb/model/object_permission.py
mwdb/model/quick_query.py
mwdb/model/tag.py
mwdb/model/user.py
mwdb/model/migrations/README
mwdb/model/migrations/alembic.ini
mwdb/model/migrations/env.py
mwdb/model/migrations/script.py.mako
mwdb/model/migrations/versions/08d1de53c2f4_missing_object_not_null_constraints.py
mwdb/model/migrations/versions/12849e43c922_new_favorites_table.py
mwdb/model/migrations/versions/1a46a79d9108_set_nullable_fk_to_correctly_delete_.py
mwdb/model/migrations/versions/1b49fefdfcb0_quick_query_to_user_relation.py
mwdb/model/migrations/versions/1cfd8137ff5e_unlimited_length_of_oidc_fields.py
mwdb/model/migrations/versions/243dede4eb74_openid_tables.py
mwdb/model/migrations/versions/25ea40a798ac_add_access_uploader_info_capability.py
mwdb/model/migrations/versions/2b4da440d3ad_missing_comment_not_null_constraints.py
mwdb/model/migrations/versions/2c44b2073670_add_index_on_comment_object_id.py
mwdb_core-2.16.1.dist-info/LICENSE
mwdb_core-2.16.1.dist-info/LICENSE.AGPL
mwdb_core-2.16.1.dist-info/METADATA
mwdb_core-2.16.1.dist-info/WHEEL
mwdb_core-2.16.1.dist-info/entry_points.txt
mwdb_core-2.16.1.dist-info/top_level.txt
mwdb_core-2.16.1.dist-info/RECORD
