Metadata-Version: 2.1
Name: mwdb-core
Version: 2.16.1
Summary: MWDB Core malware database
Home-page: https://github.com/CERT-Polska/mwdb-core
Author: CERT Polska
Author-email: info@cert.pl
Classifier: Development Status :: 5 - Production/Stable
Classifier: Operating System :: POSIX :: Linux
Classifier: Programming Language :: Python :: 3
Requires-Python: >=3.10
License-File: LICENSE
License-File: LICENSE.AGPL
Requires-Dist: Authlib ==1.6.5
Requires-Dist: Flask-Migrate ==4.0.7
Requires-Dist: Flask-SQLAlchemy ==3.0.5
Requires-Dist: Flask ==2.3.3
Requires-Dist: SQLAlchemy ==1.4.54
Requires-Dist: Werkzeug ==3.1.4
Requires-Dist: alembic ==1.14.0
Requires-Dist: apispec[marshmallow,yaml] ==6.4.0
Requires-Dist: bcrypt ==5.0.0
Requires-Dist: boto3 ==1.24.38
Requires-Dist: click-default-group ==1.2.2
Requires-Dist: click ==8.1.3
Requires-Dist: gunicorn ==23.0.0
Requires-Dist: karton-core ==5.4.0
Requires-Dist: limits ==3.9.0
Requires-Dist: luqum ==0.13.0
Requires-Dist: marshmallow ==3.20.2
Requires-Dist: prometheus-client ==0.21.1
Requires-Dist: psycopg2-binary ==2.9.10
Requires-Dist: pyJWT ==2.4.0
Requires-Dist: pycryptodomex ==3.23.0
Requires-Dist: python-dateutil ==2.8.2
Requires-Dist: python-json-logger ==2.0.2
Requires-Dist: python-magic ==0.4.18
Requires-Dist: pyzipper ==0.3.5
Requires-Dist: redis ==4.5.4
Requires-Dist: requests ==2.32.4
Requires-Dist: ssdeep ==3.4
Requires-Dist: typed-config ==1.1.0
